sinlingua/__init__.py
sinlingua/config.py
sinlingua/grammar_rule/LLM_config.py
sinlingua/grammar_rule/__init__.py
sinlingua/grammar_rule/grammar_main.py
sinlingua/grammar_rule/grammar_rules.py
sinlingua/grammar_rule/mask.py
sinlingua/grammar_rule/regression_model_for_singular_plural.py
sinlingua/grammar_rule/rule_based_1.py
sinlingua/grammar_rule/rule_based_2.py
sinlingua/grammar_rule/rule_based_3.py
sinlingua/grammar_rule/rule_based_4.py
sinlingua/grammar_rule/rule_based_future_1.py
sinlingua/grammar_rule/rule_based_past_1.py
sinlingua/grammar_rule/rule_based_past_2.py
sinlingua/grammar_rule/rule_based_past_3.py
sinlingua/grammar_rule/rule_based_plural.py
sinlingua/grammar_rule/rule_based_plural_past.py
sinlingua/grammar_rule/rule_based_singular.py
sinlingua/grammar_rule/svm_model.py
sinlingua/preprocessor/__init__.py
sinlingua/preprocessor/stemmer.py
sinlingua/preprocessor/stopword_remover.py
sinlingua/preprocessor/tokenizer.py
sinlingua/singlish/__init__.py
sinlingua/singlish/hybrid_transliterator.py
sinlingua/singlish/machine_transliterator.py
sinlingua/singlish/manual_transliterator.py
sinlingua/singlish/rulebased_transliterator.py
sinlingua/sinhala_audio/__init__.py
sinlingua/sinhala_audio/audio_to_text.py
sinlingua/src/__init__.py
sinlingua/src/grammar_rule_resources.py
sinlingua/src/preprocessor_resources.py
sinlingua/src/singlish_resources.py
sinlingua/summarizer/__init__.py
sinlingua/summarizer/bert.py
sinlingua/summarizer/faster_bert.py
sinlingua/summarizer/faster_longformer.py
sinlingua/summarizer/longformer.py
sinlingua/summarizer/tf_idf.py
sinlingua-0.1.8.dist-info/LICENSE
sinlingua-0.1.8.dist-info/METADATA
sinlingua-0.1.8.dist-info/WHEEL
sinlingua-0.1.8.dist-info/top_level.txt
sinlingua-0.1.8.dist-info/RECORD
