Metadata-Version: 2.1
Name: sinlingua
Version: 0.1.8
Summary: Package for Sinhala data processing
Author: Supun Gurusinghe, Sandaruwini Galappaththi, Supun Sarada Wijesinghe, Binura Yasodya
Author-email: supunsameeran@gmail.com, sandaruwinigalappaththi@gmail.com, saradawijesinghe@gmail.com, binurayasodya24@gmail.com
License: MIT
Project-URL: Documentation, https://sinlingua.github.io/documentation/
Project-URL: Source, https://github.com/sinlingua/sinlingua
Project-URL: Bug Tracker, https://github.com/sinlingua/sinlingua/issues
Requires-Python: >=3.7.0
License-File: LICENSE
Requires-Dist: fuzzywuzzy (==0.18.0)
Requires-Dist: gensim (==4.3.1)
Requires-Dist: googletrans (==4.0.0-rc1)
Requires-Dist: numpy (==1.23.0)
Requires-Dist: openai (==0.27.8)
Requires-Dist: pandas (==1.5.3)
Requires-Dist: pygtrie (==2.5.0)
Requires-Dist: Requests (==2.31.0)
Requires-Dist: scikit-learn (==1.1.3)
Requires-Dist: setuptools (==65.5.1)
Requires-Dist: sinling (==0.3.6)
Requires-Dist: SpeechRecognition (==3.10.0)
Requires-Dist: torch (==2.0.1)
Requires-Dist: jedi (==0.16)
Requires-Dist: transformers (==4.32.0)
